domin8/__init__.py
domin8/_version.py
domin8/document.py
domin8/dom1core.py
domin8/dom_tag.py
domin8/py.typed
domin8/svg.py
domin8/tags.py
domin8/util.py
dominate/__init__.py
dominate/_version.py
dominate/document.py
dominate/dom1core.py
dominate/dom_tag.py
dominate/py.typed
dominate/svg.py
dominate/tags.py
dominate/util.py
domin8-3.0.0rc1.dist-info/LICENSE.txt
domin8-3.0.0rc1.dist-info/METADATA
domin8-3.0.0rc1.dist-info/WHEEL
domin8-3.0.0rc1.dist-info/top_level.txt
domin8-3.0.0rc1.dist-info/RECORD
